{
  "packageName": "Hubitat Tailwind Garage Door Controller",
  "author": "dbadge",
  "version": "1.0.0",
  "minimumHEVersion": "2.2.8",
  "dateReleased": "2021-09-18",
  "drivers": [
    {
      "id": "589f710d-46f7-45ce-8f82-5b99c41eecaf",
      "name": "Tailwind Garage Door Child Device",
      "namespace": "dabtailwind-gd",
      "location": "https://raw.githubusercontent.com/Gelix/HubitatTailwind/main/tailwinddriver-child.groovy",
      "required": true
    },
    {
      "id": "2d065d15-16dc-4380-8d7a-e86438a81c7e",
      "name": "Tailwind Garage Door",
      "namespace": "dabtailwind-gd",
      "location": "https://raw.githubusercontent.com/Gelix/HubitatTailwind/main/tailwinddriver.groovy",
      "required": true
    }
  ]
}