{
  "packageName": "Hubitat Tailwind Garage Door Controller",
  "author": "dbadge",
  "version": "1.0.0",
  "minimumHEVersion": "2.2.8",
  "dateReleased": "2021-09-18",
  "drivers": [
    {
      "id": "e57874f7-a2ae-409c-9658-1cdaa5a6de46",
      "name": "Tailwind Garage Door Child Device",
      "namespace": "dabtailwind-gd",
      "location": "https://raw.githubusercontent.com/Gelix/HubitatTailwind/main/tailwinddriver-child.groovy",
      "required": true
    },
    {
      "id": "d63bc60a-d117-48d0-8bab-38fb70139687",
      "name": "Tailwind Garage Door",
      "namespace": "dabtailwind-gd",
      "location": "https://raw.githubusercontent.com/Gelix/HubitatTailwind/main/tailwinddriver.groovy",
      "required": true
    }
  ]
}